dataloop/__init__.py
dataloop/upipe/__init__.py
dataloop/upipe/__version__.py
dataloop/upipe/utils.py
dataloop/upipe/entities/__init__.py
dataloop/upipe/entities/dataframe.py
dataloop/upipe/entities/mem_queue.py
dataloop/upipe/entities/pipe.py
dataloop/upipe/entities/processor.py
dataloop/upipe/entities/worker.py
dataloop/upipe/node/__init__.py
dataloop/upipe/node/client.py
dataloop/upipe/node/manager/__init__.py
dataloop/upipe/node/manager/node_config.py
dataloop/upipe/node/manager/node_main.py
dataloop/upipe/node/manager/node_utils.py
dataloop/upipe/node/manager/pid_log.py
dataloop/upipe/node/manager/pipe_controller.py
dataloop/upipe/node/manager/processor_controller.py
dataloop/upipe/node/manager/worker_controller.py
dataloop/upipe/node/server/__init__.py
dataloop/upipe/node/server/node_controller.py
dataloop/upipe/node/server/server.py
dataloop/upipe/node/server/view_api.py
dataloop/upipe/node/server/upipe_viewer/favicon.dataloop.pipelines.svg
dataloop/upipe/node/server/upipe_viewer/favicon.ico
dataloop/upipe/node/server/upipe_viewer/index.html
dataloop/upipe/node/server/upipe_viewer/css/app.31d6cfe0.css
dataloop/upipe/node/server/upipe_viewer/css/vendor.4c53aade.css
dataloop/upipe/node/server/upipe_viewer/fonts/KFOkCnqEu92Fr1MmgVxIIzQ.9391e6e2.woff
dataloop/upipe/node/server/upipe_viewer/fonts/KFOlCnqEu92Fr1MmEU9fBBc-.ddd11dab.woff
dataloop/upipe/node/server/upipe_viewer/fonts/KFOlCnqEu92Fr1MmSU5fBBc-.877b9231.woff
dataloop/upipe/node/server/upipe_viewer/fonts/KFOlCnqEu92Fr1MmWUlfBBc-.0344cc3c.woff
dataloop/upipe/node/server/upipe_viewer/fonts/KFOlCnqEu92Fr1MmYUtfBBc-.b555d228.woff
dataloop/upipe/node/server/upipe_viewer/fonts/KFOmCnqEu92Fr1Mu4mxM.9b78ea3b.woff
dataloop/upipe/node/server/upipe_viewer/fonts/fa-brands-400.2285773e.woff
dataloop/upipe/node/server/upipe_viewer/fonts/fa-brands-400.d878b0a6.woff2
dataloop/upipe/node/server/upipe_viewer/fonts/fa-regular-400.7a333762.woff2
dataloop/upipe/node/server/upipe_viewer/fonts/fa-regular-400.bb58e57c.woff
dataloop_upipe-0.2.0.dist-info/METADATA
dataloop_upipe-0.2.0.dist-info/WHEEL
dataloop_upipe-0.2.0.dist-info/top_level.txt
dataloop_upipe-0.2.0.dist-info/RECORD
