Metadata-Version: 2.1
Name: dataloop-upipe
Version: 0.2.0
Summary: Micro Pipelines for Dataloop platform
Author: Dataloop Team
Author-email: info@dataloop.ai
Classifier: Programming Language :: Python :: 3.8
Classifier: Programming Language :: Python :: 3.9
Requires-Python: >=3.8
Requires-Dist: numpy (<=1.22.*)
Requires-Dist: fastapi (<=0.70.0)
Requires-Dist: uvicorn (<=0.15.0)
Requires-Dist: httpx (<=0.20.0)
Requires-Dist: websockets (<=10.0)
Requires-Dist: pydantic (<=1.8.2)
Requires-Dist: python-multipart
Requires-Dist: aiohttp (<=3.7.4.post0)
Requires-Dist: psutil (<=5.8.0)
Requires-Dist: starlette (<=0.16.0)
Requires-Dist: opencv-python (<=4.5.3.56)
Requires-Dist: colorama (<=0.4.4)
Requires-Dist: websocket-client (<=1.2.1)
Requires-Dist: requests (<=2.26.0)
